Metadata-Version: 2.1
Name: cugraph-cuda92
Version: 0.6.0
Summary: cuGraph - RAPIDS Graph Analytic Algorithms
Home-page: https://github.com/rapidsai/cugraph
Author: NVIDIA Corporation
License: Apache
Platform: UNKNOWN
Classifier: Intended Audience :: Developers
Classifier: Programming Language :: Python
Classifier: Programming Language :: Python :: 3.6
Classifier: Programming Language :: Python :: 3.7
Requires-Dist: numpy
Requires-Dist: cython
